fwakit/__init__.py
fwakit/cli.py
fwakit/dem.py
fwakit/epa_waters.py
fwakit/fwa.py
fwakit/settings.py
fwakit/sources.json
fwakit/util.py
fwakit/watersheds.py
fwakit/watersheds_arcgis.py
fwakit/sql/CDB_Hexagon.sql
fwakit/sql/all_waterbody_polys_prelim.sql
fwakit/sql/create_fwa_named_streams.sql
fwakit/sql/create_fwa_waterbodies.sql
fwakit/sql/create_fwa_watershed_groups_subdivided.sql
fwakit/sql/create_invalid_codes.sql
fwakit/sql/create_lut_50k_20k_wsc.sql
fwakit/sql/events_to_lines.sql
fwakit/sql/events_to_points.sql
fwakit/sql/fwa_downstream.sql
fwakit/sql/fwa_downstreamlength.sql
fwakit/sql/fwa_downstreamlength_recursive.sql
fwakit/sql/fwa_downstreamwsc.sql
fwakit/sql/fwa_elevation.sql
fwakit/sql/fwa_geomupstream.sql
fwakit/sql/fwa_lengthdownstream.sql
fwakit/sql/fwa_lengthdownstream_recursive.sql
fwakit/sql/fwa_lengthinstream.sql
fwakit/sql/fwa_lengthupstream.sql
fwakit/sql/fwa_slope.sql
fwakit/sql/fwa_slopewindow.sql
fwakit/sql/fwa_streamslope.sql
fwakit/sql/fwa_streamslope_test.sql
fwakit/sql/fwa_trimwsc.sql
fwakit/sql/fwa_upstreamlength.sql
fwakit/sql/fwa_upstreamwsc.sql
fwakit/sql/fwa_wsc2ltree.sql
fwakit/sql/get_local_code.sql
fwakit/sql/locate_point_on_stream.sql
fwakit/sql/populate_gradient.sql
fwakit/sql/reference_points.sql
fwakit/sql/streams_closest_to_point.sql
fwakit/sql/t.sql
fwakit/sql/test.sql
fwakit/sql/test_observations.sql
fwakit/sql/upstream_border_crossing.sql
fwakit/sql/wsdrefine_hexwsd.sql
fwakit/sql/wsdrefine_length_to_top_bottom.sql
fwakit/sql/wsdrefine_norefine.sql
fwakit/sql/wsdrefine_river_wsd_cut.sql
fwakit/sql/wsdrefine_river_wsd_cut_bk.sql
fwakit/sql/wsdrefine_river_wsd_cut_remove.sql
fwakit/sql/wsdrefine_streams.sql
fwakit-0.0.2.dist-info/LICENSE.txt
fwakit-0.0.2.dist-info/METADATA
fwakit-0.0.2.dist-info/WHEEL
fwakit-0.0.2.dist-info/entry_points.txt
fwakit-0.0.2.dist-info/top_level.txt
fwakit-0.0.2.dist-info/RECORD
