Metadata-Version: 2.1
Name: fwakit
Version: 0.0.2
Summary: Python / PostgreSQL tools for working with BC Freshwater Atlas
Home-page: https://github.com/smnorris/fwakit
Author: Simon Norris
Author-email: snorris@hillcrestgeo.ca
License: MIT
Keywords: gis FWA "Freshwater Atlas" BC "British Columbia" streams watersheds
Platform: UNKNOWN
Classifier: Development Status :: 3 - Alpha
Classifier: Intended Audience :: Developers
Classifier: License :: OSI Approved :: MIT License
Classifier: Operating System :: OS Independent
Classifier: Programming Language :: Python :: 2.7
Classifier: Programming Language :: Python :: 3.3
Classifier: Programming Language :: Python :: 3.4
Classifier: Programming Language :: Python :: 3.5
Classifier: Programming Language :: Python :: 3.6
Requires-Dist: bcdata
Requires-Dist: click
Requires-Dist: geojson
Requires-Dist: pgdata
Requires-Dist: requests
Requires-Dist: shapely
Requires-Dist: sqlalchemy
Provides-Extra: test
Requires-Dist: pytest ; extra == 'test'
Requires-Dist: coverage ; extra == 'test'
